pytunegrab/__init__.py
pytunegrab/core.py
pytunegrab-0.1.1.dist-info/METADATA
pytunegrab-0.1.1.dist-info/WHEEL
pytunegrab-0.1.1.dist-info/top_level.txt
pytunegrab-0.1.1.dist-info/RECORD
