Metadata-Version: 2.1
Name: pytunegrab
Version: 0.1.1
Requires-Dist: aiofiles
Requires-Dist: certifi
Requires-Dist: charset-normalizer
Requires-Dist: colorama
Requires-Dist: decorator
Requires-Dist: docutils
Requires-Dist: idna
Requires-Dist: imageio
Requires-Dist: imageio-ffmpeg
Requires-Dist: importlib-metadata
Requires-Dist: jaraco.classes
Requires-Dist: keyring
Requires-Dist: markdown-it-py
Requires-Dist: mdurl
Requires-Dist: more-itertools
Requires-Dist: moviepy
Requires-Dist: nh3
Requires-Dist: numpy
Requires-Dist: pillow
Requires-Dist: pkginfo
Requires-Dist: proglog
Requires-Dist: Pygments
Requires-Dist: python-slugify
Requires-Dist: pytube
Requires-Dist: pywin32-ctypes
Requires-Dist: readme-renderer
Requires-Dist: requests
Requires-Dist: requests-toolbelt
Requires-Dist: rfc3986
Requires-Dist: rich
Requires-Dist: setuptools
Requires-Dist: slugify
Requires-Dist: text-unidecode
Requires-Dist: tqdm
Requires-Dist: twine
Requires-Dist: urllib3
Requires-Dist: zipp
